[
	
	{  
		"name":       "Indian",   
		"type":      ["main"],   
		"url":       "https://dev-gpsoft.github.io/assets/home/recipes.github.io/indian.json",
		"image":     "https://dev-gpsoft.github.io/assets/home/recipes.github.io/assets/home/ni.png" 
    },
	{  
		"name":       "Chinese",   
		"type":      ["main"],   
		"image":    "https://dev-gpsoft.github.io/assets/home/recipes.github.io/assets/home/chinese.png" 
    },
	{  
		"name":       "Italian",   
		"type":      ["main"],   
		"image":    "https://dev-gpsoft.github.io/assets/home/recipes.github.io/assets/home/italian.png" 
    },
	{  
		"name":       "British",   
		"type":      ["main"],   
		"image":    "https://dev-gpsoft.github.io/assets/home/recipes.github.io/assets/home/british.png" 
    },
	{  
		"name":       "French",   
		"type":      ["main"],   
		"image":    "https://dev-gpsoft.github.io/assets/home/recipes.github.io/assets/home/french.png" 
    },
	{  
		"name":       "American",   
		"type":      ["main"],   
		"image":    "https://dev-gpsoft.github.io/assets/home/recipes.github.io/assets/home/american.png" 
    },
	{  
		"name":       "Mexican",   
		"type":      ["main"],   
		"image":    "https://dev-gpsoft.github.io/assets/home/recipes.github.io/assets/home/mexican.png" 
    },
	{  
		"name":       "Arabic",   
		"type":      ["main"],   
		"image":    "https://dev-gpsoft.github.io/assets/home/recipes.github.io/assets/home/arabic.png" 
    },
	{  
		"name":       "Japanese",   
		"type":      ["main"],   
		"image":    "https://dev-gpsoft.github.io/assets/home/recipes.github.io/assets/home/japanese.png" 
    },
	{  
		"name":       "Thai",   
		"type":      ["main"],   
		"image":    "https://dev-gpsoft.github.io/assets/home/recipes.github.io/assets/home/thai.png" 
    },
	{  
		"name":       "Malaysian",   
		"type":      ["main"],   
		"image":    "https://dev-gpsoft.github.io/assets/home/recipes.github.io/assets/home/malaysian.png" 
    },
	{  
		"name":       "Spanish",   
		"type":      ["main"],   
		"image":    "https://dev-gpsoft.github.io/assets/home/recipes.github.io/assets/home/spainsh.png" 
    },
	{  
		"name":       "Korean",   
		"type":      ["main"],   
		"image":    "https://dev-gpsoft.github.io/assets/home/recipes.github.io/assets/home/korean.png" 
    },
	{  
		"name":       "Pakistani",   
		"type":      ["main"],   
		"image":    "https://dev-gpsoft.github.io/assets/home/recipes.github.io/assets/home/pakistani.png" 
    },
	{  
		"name":       "Latino",   
		"type":      ["main"],   
		"image":    "https://dev-gpsoft.github.io/assets/home/recipes.github.io/assets/home/latino.png" 
    }
	
]